queue_processor/__init__.py
queue_processor-1.1.2.dist-info/LICENSE
queue_processor-1.1.2.dist-info/METADATA
queue_processor-1.1.2.dist-info/WHEEL
queue_processor-1.1.2.dist-info/top_level.txt
queue_processor-1.1.2.dist-info/RECORD
