Metadata-Version: 2.1
Name: queue_processor
Version: 1.1.2
Summary: Python3 thread based async queue manager
Author-email: Thomas Dunteman <git@learningtopi.com>
Project-URL: homepage, https://www.learningtopi.com/python-modules-applications/queue_processor/
Project-URL: bug tracker, https://github.com/LearningToPi/queue_processor/issues
Project-URL: source code, https://github.com/LearningToPi/queue_processor
Keywords: queue,thread,async
Classifier: License :: OSI Approved :: MIT License
Classifier: Programming Language :: Python :: 3
Classifier: Topic :: Software Development :: Libraries :: Python Modules
Requires-Python: >=3.6
License-File: LICENSE
Requires-Dist: logging-handler
Requires-Dist: parameter-verification
